brushtail/__init__.py
brushtail/browser.py
brushtail/checkpoints.py
brushtail-0.0.2.dist-info/LICENSE
brushtail-0.0.2.dist-info/METADATA
brushtail-0.0.2.dist-info/WHEEL
brushtail-0.0.2.dist-info/top_level.txt
brushtail-0.0.2.dist-info/RECORD
