Metadata-Version: 2.1
Name: brushtail
Version: 0.0.2
Summary: A small python framework for making simple, maintainable web scraping scripts.
Home-page: https://github.com/EthanVellacott/brushtail
Author: Ethan Vellacott
License: Copyright (c) 2018 The Python Packaging Authority
Project-URL: Homepage, https://github.com/EthanVellacott/brushtail
Project-URL: Issues, https://github.com/EthanVellacott/brushtail/issues
Classifier: Programming Language :: Python :: 3
Classifier: License :: OSI Approved :: MIT License
Classifier: Operating System :: OS Independent
Requires-Python: >=3.11
License-File: LICENSE
Requires-Dist: requests
Requires-Dist: selenium
Requires-Dist: beautifulsoup4
